vinormx/__init__.py
vinormx/benchmark_vinormx.py
vinormx/build.py
vinormx/comprehensive_performance_test.py
vinormx/config_module.py
vinormx/dict_module.py
vinormx/mapping_module.py
vinormx/regex_rule_module.py
vinormx/setup.py
vinormx/test_vinormx.py
vinormx/vinormx.py
vinormx/Dict/Popular.txt
vinormx/RegexRule/Codenumber.txt
vinormx/RegexRule/Date_1.txt
vinormx/RegexRule/Date_2.txt
vinormx/RegexRule/Date_3.txt
vinormx/RegexRule/Date_From_To_1.txt
vinormx/RegexRule/Date_From_To_2.txt
vinormx/RegexRule/Email.txt
vinormx/RegexRule/FootballOther.txt
vinormx/RegexRule/FootballUnder.txt
vinormx/RegexRule/Hour_1.txt
vinormx/RegexRule/Measurement.txt
vinormx/RegexRule/Measurement_1.txt
vinormx/RegexRule/Month.txt
vinormx/RegexRule/NormalNumber.txt
vinormx/RegexRule/Office.txt
vinormx/RegexRule/PhoneNumber.txt
vinormx/RegexRule/PoliticalDivision.txt
vinormx/RegexRule/RomanNumber.txt
vinormx/RegexRule/Street.txt
vinormx/RegexRule/Time.txt
vinormx/RegexRule/Website.txt
vinormx/dictionaries/abbreviation_dict.txt
vinormx/dictionaries/acronyms_dict.txt
vinormx/dictionaries/base_unit_dict.txt
vinormx/dictionaries/currency_dict.txt
vinormx/dictionaries/letter_sound_dict.txt
vinormx/dictionaries/letter_sound_vn_dict.txt
vinormx/dictionaries/month_dict.txt
vinormx/dictionaries/number_dict.txt
vinormx/dictionaries/prefix_unit_dict.txt
vinormx/dictionaries/special_chars_dict.txt
vinormx/dictionaries/symbol_dict.txt
vinormx/dictionaries/teencode_dict.txt
vinormx/dictionaries/unit_dict.txt
vinormx-1.0.8.dist-info/licenses/LICENSE
vinormx-1.0.8.dist-info/METADATA
vinormx-1.0.8.dist-info/WHEEL
vinormx-1.0.8.dist-info/entry_points.txt
vinormx-1.0.8.dist-info/top_level.txt
vinormx-1.0.8.dist-info/RECORD
