Metadata-Version: 2.4
Name: vinormx
Version: 1.0.8
Summary: Advanced Vietnamese Text Normalization System - Modular Architecture with Comprehensive Dictionaries and Regex Rules
Home-page: https://github.com/genievn/vinormx
Author: Nguyen Huu Thanh
Author-email: nguyenhuuthanh@gmail.com
Project-URL: Bug Reports, https://github.com/genievn/vinormx/issues
Project-URL: Source, https://github.com/genievn/vinormx
Project-URL: Original Vinorm, https://github.com/v-nhandt21/Vinorm
Project-URL: Original C++ Version, https://github.com/NoahDrisort/vinorm_cpp_version
Keywords: vietnamese text normalization nlp tts speech synthesis modular comprehensive dictionaries regex rules
Classifier: Development Status :: 4 - Beta
Classifier: Intended Audience :: Developers
Classifier: Intended Audience :: Science/Research
Classifier: License :: OSI Approved :: MIT License
Classifier: Operating System :: OS Independent
Classifier: Programming Language :: Python :: 3
Classifier: Programming Language :: Python :: 3.6
Classifier: Programming Language :: Python :: 3.7
Classifier: Programming Language :: Python :: 3.8
Classifier: Programming Language :: Python :: 3.9
Classifier: Programming Language :: Python :: 3.10
Classifier: Programming Language :: Python :: 3.11
Classifier: Programming Language :: Python :: 3.12
Classifier: Topic :: Scientific/Engineering :: Artificial Intelligence
Classifier: Topic :: Text Processing :: Linguistic
Classifier: Topic :: Software Development :: Libraries :: Python Modules
Classifier: Natural Language :: Vietnamese
Requires-Python: >=3.6
License-File: LICENSE
Provides-Extra: dev
Requires-Dist: pytest>=6.0; extra == "dev"
Requires-Dist: pytest-cov; extra == "dev"
Requires-Dist: black; extra == "dev"
Requires-Dist: flake8; extra == "dev"
Dynamic: author
Dynamic: author-email
Dynamic: classifier
Dynamic: description
Dynamic: description-content-type
Dynamic: home-page
Dynamic: keywords
Dynamic: license-file
Dynamic: project-url
Dynamic: provides-extra
Dynamic: requires-python
Dynamic: summary
